{
  "updated": "2026-02-21T04:57:08.284Z",
  "total": 3,
  "results": [
    {
      "url": "https://raw.githubusercontent.com/liketolivefree/kobabi/main/sub.txt",
      "status": "healthy",
      "latency": 300,
      "speedMbps": 247
    },
    {
      "url": "https://raw.githubusercontent.com/youfoundamin/V2rayCollector/main/ss_iran.txt",
      "status": "healthy",
      "latency": 131,
      "speedMbps": 399
    },
    {
      "url": "https://raw.githubusercontent.com/youfoundamin/V2rayCollector/main/vless_iran.txt",
      "status": "healthy",
      "latency": 123,
      "speedMbps": 5196
    }
  ]
}